{
  "id": "dip_health_rec_pastpapers_archive_1769461208460_384d8146-433a-4fb9-a3cc-fec295a16cf5_jan2023",
  "title": "Quiz: FQE January 2023 Past Paper",
  "subjectId": "dip_health_rec_pastpapers_archive_1769461208460",
  "topicId": "384d8146-433a-4fb9-a3cc-fec295a16cf5",
  "topicName": "Health Records Management Collection",
  "description": "Full Final Qualifying Examination from January 2023 covering MCQs, Short Answer, and Long Answer questions.",
  "isPaid": true,
  "timeLimit": 180,
  "passingScore": 70,
  "version": 1,
  "order": 1,
  "questions": [
    {
      "id": "q1",
      "type": "multiple-choice",
      "question": "Listed below are ways of conveying information to the waiting list except?",
      "points": 1,
      "options": [
        { "id": "a", "text": "Card created for every patient", "isCorrect": true },
        { "id": "b", "text": "Nurse or physician sending list of patients to be added to the waiting list", "isCorrect": false },
        { "id": "c", "text": "Letter from a consultant", "isCorrect": false },
        { "id": "d", "text": "Letter from in-patient department", "isCorrect": false }
      ],
      "explanation": "The waiting list is a mechanism for scheduling patients. Information is conveyed via referrals or direct requests, not by creating a card for 'every' patient indiscriminately.",
      "hint": "Think about which method is too general and not specific to a waiting list request."
    },
    {
      "id": "q2",
      "type": "multiple-choice",
      "question": "There are different types of health records indices used and maintained in a health records department, these include the following except?",
      "points": 1,
      "options": [
        { "id": "a", "text": "The outpatient index", "isCorrect": false },
        { "id": "b", "text": "The disease index", "isCorrect": false },
        { "id": "c", "text": "The operation index", "isCorrect": false },
        { "id": "d", "text": "The waiting list index", "isCorrect": true }
      ],
      "explanation": "Standard indices (Disease, Operation, Physician) facilitate research and retrieval. A 'waiting list' is a scheduling tool/register, not a primary index used for retrospective data retrieval.",
      "hint": "Which one is used for scheduling rather than researching past cases?"
    },
    {
      "id": "q3",
      "type": "multiple-choice",
      "question": "The following are checks to be made on the waiting list except?",
      "points": 1,
      "options": [
        { "id": "a", "text": "Checking for completeness", "isCorrect": false },
        { "id": "b", "text": "Checking for accuracy", "isCorrect": false },
        { "id": "c", "text": "Checking for quality", "isCorrect": true },
        { "id": "d", "text": "Checking for duplication", "isCorrect": false }
      ],
      "explanation": "Administrative list maintenance focuses on Completeness, Accuracy, and De-duplication. 'Quality' is a broad clinical or service concept, not a specific clerical check on a list entry.",
      "hint": "Three options refer to data integrity; one refers to a broader abstract concept."
    },
    {
      "id": "q4",
      "type": "multiple-choice",
      "question": "Which of the following is not a quality of a Health Records and Information Officer?",
      "points": 1,
      "options": [
        { "id": "a", "text": "Integrity", "isCorrect": false },
        { "id": "b", "text": "Generosity", "isCorrect": true },
        { "id": "c", "text": "Humility", "isCorrect": false },
        { "id": "d", "text": "Adaptability", "isCorrect": false }
      ],
      "explanation": "Professional qualities include Integrity, Adaptability, and Discretion (Humility). Generosity is a personal virtue but not a professional requirement for records management.",
      "hint": "Which trait is a personal kindness rather than a professional standard?"
    },
    {
      "id": "q5",
      "type": "multiple-choice",
      "question": "The following are permanent records, which one is not?",
      "points": 1,
      "options": [
        { "id": "a", "text": "Maternity records", "isCorrect": true },
        { "id": "b", "text": "Registers of birth", "isCorrect": false },
        { "id": "c", "text": "Registers of death", "isCorrect": false },
        { "id": "d", "text": "Registers of surgical procedures", "isCorrect": false }
      ],
      "explanation": "Registers (Birth, Death, Surgical) are statutory permanent records. Maternity records have a long retention period (e.g., 25 years) but are not classified as 'permanent' registers.",
      "hint": "Distinguish between a patient case file and a statutory register."
    },
    {
      "id": "q6",
      "type": "multiple-choice",
      "question": "Case records can be stated as ____.",
      "points": 1,
      "options": [
        { "id": "a", "text": "Records initiated for patients who got admitted into the wards and attend consultative clinics", "isCorrect": true },
        { "id": "b", "text": "Patients who continuously attend the consultant clinic", "isCorrect": false },
        { "id": "c", "text": "The person taking in the information", "isCorrect": false },
        { "id": "d", "text": "The range of documents to be included in the case records", "isCorrect": false }
      ],
      "explanation": "Case records cover the clinical history for both inpatient (ward) and outpatient (clinic) episodes.",
      "hint": "Look for the definition that covers both admission and clinic attendance."
    },
    {
      "id": "q7",
      "type": "multiple-choice",
      "question": "The common tracer card has the following information written on it except?",
      "points": 1,
      "options": [
        { "id": "a", "text": "Patient's full name", "isCorrect": false },
        { "id": "b", "text": "Date of appointment", "isCorrect": false },
        { "id": "c", "text": "Destination i.e. Ward, clinic", "isCorrect": false },
        { "id": "d", "text": "Patients date of birth", "isCorrect": true }
      ],
      "explanation": "A tracer card needs to identify the file (Name/Number) and where it went (Destination/Date). Date of Birth is not critical for the temporary tracking function.",
      "hint": "Which piece of information doesn't help locate where the file went?"
    },
    {
      "id": "q8",
      "type": "multiple-choice",
      "question": "Auxiliary equipment includes the following except?",
      "points": 1,
      "options": [
        { "id": "a", "text": "Filling trolleys", "isCorrect": false },
        { "id": "b", "text": "Ladders", "isCorrect": false },
        { "id": "c", "text": "Dividers", "isCorrect": true },
        { "id": "d", "text": "Preparation tables", "isCorrect": false }
      ],
      "explanation": "Trolleys, ladders, and tables are auxiliary equipment. Dividers are filing supplies/consumables used within the system.",
      "hint": "Which item is a supply placed inside the shelf rather than a tool used to do the work?"
    },
    {
      "id": "q9",
      "type": "multiple-choice",
      "question": "The most economical filling method as far as space is concerned is?",
      "points": 1,
      "options": [
        { "id": "a", "text": "Mobile racking", "isCorrect": true },
        { "id": "b", "text": "Suspended filing", "isCorrect": false },
        { "id": "c", "text": "filling cabinets", "isCorrect": false },
        { "id": "d", "text": "Shelve filing", "isCorrect": false }
      ],
      "explanation": "Mobile racking (Compactus) eliminates fixed aisles, saving up to 50% of floor space compared to static shelving.",
      "hint": "Which system moves on rails to eliminate aisles?"
    },
    {
      "id": "q10",
      "type": "multiple-choice",
      "question": "Which of the following principles in medical practice entitles patients equity and fairness?",
      "points": 1,
      "options": [
        { "id": "a", "text": "Autonomy", "isCorrect": false },
        { "id": "b", "text": "Fidelity", "isCorrect": false },
        { "id": "c", "text": "Justice", "isCorrect": true },
        { "id": "d", "text": "Beneficence", "isCorrect": false }
      ],
      "explanation": "Justice refers to fairness, equity, and impartial distribution of resources.",
      "hint": "Think of the legal term for fairness."
    },
    {
      "id": "q11",
      "type": "multiple-choice",
      "question": "Which of the following requirements is not to be considered when establishing a health records department?",
      "points": 1,
      "options": [
        { "id": "a", "text": "Location of the department", "isCorrect": false },
        { "id": "b", "text": "Space requirement for records", "isCorrect": false },
        { "id": "c", "text": "System of communication within the department and other departments", "isCorrect": false },
        { "id": "d", "text": "System to ensure transportation of files within the department and other departments", "isCorrect": true }
      ],
      "explanation": "While important, specific file transportation systems are operational details. Location, Space, and Communication are fundamental strategic establishment requirements.",
      "hint": "Which option is an operational logistical detail rather than a structural requirement?"
    },
    {
      "id": "q12",
      "type": "multiple-choice",
      "question": "__________ is the arrangement of all forms inside the unit folder in a prescribed manner",
      "points": 1,
      "options": [
        { "id": "a", "text": "Editing", "isCorrect": true },
        { "id": "b", "text": "Auditing", "isCorrect": false },
        { "id": "c", "text": "Monitoring", "isCorrect": false },
        { "id": "d", "text": "Evaluation", "isCorrect": false }
      ],
      "explanation": "Editing (or assembly) involves checking and arranging the documents in a specific order (chronological or source-oriented) after discharge.",
      "hint": "This process happens before permanent filing to tidy up the record."
    },
    {
      "id": "q13",
      "type": "multiple-choice",
      "question": "Health records are primarily used for?",
      "points": 1,
      "options": [
        { "id": "a", "text": "Research and training", "isCorrect": false },
        { "id": "b", "text": "Continuity of patient care", "isCorrect": true },
        { "id": "c", "text": "Coding and indexing", "isCorrect": false },
        { "id": "d", "text": "Planning and budgeting", "isCorrect": false }
      ],
      "explanation": "The primary purpose of the record is to document care for the patient's ongoing treatment (continuity). Research and billing are secondary uses.",
      "hint": "What is the most immediate reason a doctor writes notes?"
    },
    {
      "id": "q14",
      "type": "multiple-choice",
      "question": "Records are necessary for the practice of _________ as Medication and for effective treatment",
      "points": 1,
      "options": [
        { "id": "a", "text": "Earliest antiquity", "isCorrect": false },
        { "id": "b", "text": "The history of heath records", "isCorrect": false },
        { "id": "c", "text": "Medicine", "isCorrect": true },
        { "id": "d", "text": "The history", "isCorrect": false }
      ],
      "explanation": "The full quote is: 'Records are necessary for the practice of Medicine as Medication is for effective treatment.'",
      "hint": "Complete the sentence logically: Records help practice..."
    },
    {
      "id": "q15",
      "type": "multiple-choice",
      "question": "Diagnostic records:",
      "points": 1,
      "options": [
        { "id": "a", "text": "They include notes on Radiography, pathology and other investigations", "isCorrect": true },
        { "id": "b", "text": "They are usually initiated by consultative forms", "isCorrect": false },
        { "id": "c", "text": "These forms are usually 6\" x 4\" in size and are available in all morgue rooms", "isCorrect": false },
        { "id": "d", "text": "They are in-patient department in a health care facility", "isCorrect": false }
      ],
      "explanation": "Diagnostic records specifically refer to reports from diagnostic services like X-ray (radiography) and Labs (pathology).",
      "hint": "Which department helps 'diagnose' through images and tests?"
    },
    {
      "id": "q16",
      "type": "multiple-choice",
      "question": "____ are the basic concepts and fundamental principles of decent human conduct?",
      "points": 1,
      "options": [
        { "id": "a", "text": "Professional", "isCorrect": false },
        { "id": "b", "text": "Professional ethics", "isCorrect": true },
        { "id": "c", "text": "Code professionals", "isCorrect": false },
        { "id": "d", "text": "Principles", "isCorrect": false }
      ],
      "explanation": "Ethics refers to moral principles of decent conduct. In a work setting, this is Professional Ethics.",
      "hint": "It deals with right and wrong behavior in a profession."
    },
    {
      "id": "q17",
      "type": "multiple-choice",
      "question": "The first real physician of health records in Egypt is?",
      "points": 1,
      "options": [
        { "id": "a", "text": "Edwin Smith", "isCorrect": false },
        { "id": "b", "text": "Hippocrates", "isCorrect": false },
        { "id": "c", "text": "Imhotep", "isCorrect": true },
        { "id": "d", "text": "Franklin", "isCorrect": false }
      ],
      "explanation": "Imhotep (c. 2600 BC) is the earliest known physician by name and is associated with the first systematic medical records in Egypt.",
      "hint": "He was an Egyptian polymath and architect of the Step Pyramid."
    },
    {
      "id": "q18",
      "type": "multiple-choice",
      "question": "Hippocrates was known for the below mentioned except",
      "points": 1,
      "options": [
        { "id": "a", "text": "First to cast out superstition", "isCorrect": false },
        { "id": "b", "text": "Practice medicine on scientific principles", "isCorrect": false },
        { "id": "c", "text": "Author of the Hippocratic oath", "isCorrect": false },
        { "id": "d", "text": "Grand vizier", "isCorrect": true }
      ],
      "explanation": "Hippocrates was a Greek physician. 'Grand Vizier' is a title associated with Ancient Egypt (Imhotep) or Ottoman officials, not Greek medicine.",
      "hint": "Which title belongs to an Egyptian or Ottoman official, not a Greek doctor?"
    },
    {
      "id": "q19",
      "type": "multiple-choice",
      "question": "Informal admission refers to?",
      "points": 1,
      "options": [
        { "id": "a", "text": "A patient is admitted voluntarily, he or she is aware he has mental illness", "isCorrect": false },
        { "id": "b", "text": "A patient is admitted without legal or other formalities and the hospital has no right to detain him against his will", "isCorrect": true },
        { "id": "c", "text": "A patient is admitted with legal formalities", "isCorrect": false },
        { "id": "d", "text": "Patient is admitted involuntarily", "isCorrect": false }
      ],
      "explanation": "Informal admission is voluntary. The key distinction is the patient is free to leave (no detention rights).",
      "hint": "Think 'Voluntary' and 'No formalities'."
    },
    {
      "id": "q20",
      "type": "multiple-choice",
      "question": "Wide spread implementation of electronic records has been hampered by perceived barriers including one of the following",
      "points": 1,
      "options": [
        { "id": "a", "text": "Efficiency", "isCorrect": false },
        { "id": "b", "text": "Encouragement", "isCorrect": false },
        { "id": "c", "text": "Empowerment", "isCorrect": false },
        { "id": "d", "text": "Incompatibility", "isCorrect": true }
      ],
      "explanation": "Incompatibility (or lack of interoperability) between different systems is a major barrier. The others are positive outcomes.",
      "hint": "Which one is a technical problem?"
    },
    {
      "id": "q21",
      "type": "multiple-choice",
      "question": "One of the following statements in not true about subpoena",
      "points": 1,
      "options": [
        { "id": "a", "text": "Is the term used for legal order to produce records to a court", "isCorrect": false },
        { "id": "b", "text": "It is usually addressed to the custodian of medical records", "isCorrect": false },
        { "id": "c", "text": "If a subpoena or court order is served it must not be obeyed", "isCorrect": true },
        { "id": "d", "text": "It directs the person to appear in a given court with the records", "isCorrect": false }
      ],
      "explanation": "A subpoena MUST be obeyed. Disobeying it leads to contempt of court.",
      "hint": "Can you ignore a court order?"
    },
    {
      "id": "q22",
      "type": "multiple-choice",
      "question": "The type of tracing system where the card may be used many times for multiple records is called?",
      "points": 1,
      "options": [
        { "id": "a", "text": "Master tracing card", "isCorrect": false },
        { "id": "b", "text": "Personal tracing card", "isCorrect": false },
        { "id": "c", "text": "Common tracer card", "isCorrect": true },
        { "id": "d", "text": "Appointed tracer card", "isCorrect": false }
      ],
      "explanation": "A common tracer card is generic and reusable for any file.",
      "hint": "Which word implies it can be shared or used by all?"
    },
    {
      "id": "q23",
      "type": "multiple-choice",
      "question": "Which of the following is a quality of a good appraiser?",
      "points": 1,
      "options": [
        { "id": "a", "text": "Professional responsibility", "isCorrect": false },
        { "id": "b", "text": "Knowledge and understanding", "isCorrect": false },
        { "id": "c", "text": "Professional judgement", "isCorrect": true },
        { "id": "d", "text": "Well educated", "isCorrect": false }
      ],
      "explanation": "An appraiser needs Professional Judgment to evaluate the value of records for retention or destruction.",
      "hint": "What specific mental skill is needed to make decisions about value?"
    },
    {
      "id": "q24",
      "type": "multiple-choice",
      "question": "Which of the following is not an important step in determining the amount of space required for medical records files?",
      "points": 1,
      "options": [
        { "id": "a", "text": "Measure of full shelf and count the number on the shelf", "isCorrect": false },
        { "id": "b", "text": "Calculate the number of files per linear meter", "isCorrect": false },
        { "id": "c", "text": "Estimate the number of personnel required", "isCorrect": true },
        { "id": "d", "text": "Estimate the number of outpatient registration, deaths and discharges", "isCorrect": false }
      ],
      "explanation": "Personnel numbers affect office space, not the physical storage capacity needed for the files themselves.",
      "hint": "Which option relates to staff rather than physical file volume?"
    },
    {
      "id": "q25",
      "type": "multiple-choice",
      "question": "The section where when patient arrives in health care facility is greeted and welcomed to the hospital,",
      "points": 1,
      "options": [
        { "id": "a", "text": "Registration", "isCorrect": false },
        { "id": "b", "text": "Reception", "isCorrect": true },
        { "id": "c", "text": "Admission", "isCorrect": false },
        { "id": "d", "text": "Discharge", "isCorrect": false }
      ],
      "explanation": "Reception is the initial greeting point.",
      "hint": "Where do you first report upon arrival?"
    },
    {
      "id": "q26",
      "type": "multiple-choice",
      "question": "There are different types of health records that are generated from medical facility and they are grouped into the following categories, which one is not?",
      "points": 1,
      "options": [
        { "id": "a", "text": "Case records", "isCorrect": false },
        { "id": "b", "text": "Out patient records", "isCorrect": false },
        { "id": "c", "text": "Patient records", "isCorrect": true },
        { "id": "d", "text": "Diagnostic records", "isCorrect": false }
      ],
      "explanation": "'Patient records' is the umbrella term for all of them, not a specific sub-category like Case or Outpatient records.",
      "hint": "Which term describes the whole group rather than a part?"
    },
    {
      "id": "q27",
      "type": "multiple-choice",
      "question": "In the process of initiating a patient record, the following details must appear except",
      "points": 1,
      "options": [
        { "id": "a", "text": "Date", "isCorrect": false },
        { "id": "b", "text": "Full name of the patient", "isCorrect": false },
        { "id": "c", "text": "Sex", "isCorrect": false },
        { "id": "d", "text": "Address", "isCorrect": true }
      ],
      "explanation": "While address is important, Name, Sex, and Date are critical for clinical identification on the sheet itself. Address is often stored in the registration system.",
      "hint": "Which detail is demographic contact info rather than immediate identification?"
    },
    {
      "id": "q28",
      "type": "multiple-choice",
      "question": "It is at the _______ that new patients/clients get their first impression of the institution values, neatness, cleanliness, taste and consideration for patient comfort",
      "points": 1,
      "options": [
        { "id": "a", "text": "Reception", "isCorrect": true },
        { "id": "b", "text": "Ward", "isCorrect": false },
        { "id": "c", "text": "Library", "isCorrect": false },
        { "id": "d", "text": "Admission", "isCorrect": false }
      ],
      "explanation": "The Reception is the 'face' of the hospital where first impressions are formed.",
      "hint": "Where does the patient interaction begin?"
    },
    {
      "id": "q29",
      "type": "multiple-choice",
      "question": "In terminal digit filing system, the growth is not at one end because?",
      "points": 1,
      "options": [
        { "id": "a", "text": "It is the easier way of filling", "isCorrect": false },
        { "id": "b", "text": "Busiest section of the library", "isCorrect": false },
        { "id": "c", "text": "It is used by the United States hospital", "isCorrect": false },
        { "id": "d", "text": "The library is divided into 100 major sections", "isCorrect": true }
      ],
      "explanation": "TDF distributes records evenly across 100 sections (00-99), preventing congestion at the end.",
      "hint": "How many sections does Terminal Digit Filing use?"
    },
    {
      "id": "q30",
      "type": "multiple-choice",
      "question": "Sources of admission include the following except?",
      "points": 1,
      "options": [
        { "id": "a", "text": "Other hospitals", "isCorrect": false },
        { "id": "b", "text": "In-patient clinic", "isCorrect": true },
        { "id": "c", "text": "Outpatient clinic", "isCorrect": false },
        { "id": "d", "text": "Waiting list", "isCorrect": false }
      ],
      "explanation": "In-patient clinic is a contradictory term. Clinics are outpatient; Wards are inpatient.",
      "hint": "Clinics are for outpatients, not inpatients."
    },
    {
      "id": "q31",
      "type": "multiple-choice",
      "question": "All offices should comply with precaution",
      "points": 1,
      "options": [
        { "id": "a", "text": "Security", "isCorrect": false },
        { "id": "b", "text": "Fire", "isCorrect": true },
        { "id": "c", "text": "Space", "isCorrect": false },
        { "id": "d", "text": "Storage", "isCorrect": false }
      ],
      "explanation": "Fire precautions are mandatory safety requirements for all offices.",
      "hint": "Think about safety emergencies."
    },
    {
      "id": "q32",
      "type": "multiple-choice",
      "question": "Which of the following is not a procedure for disposal of dead bodies?",
      "points": 1,
      "options": [
        { "id": "a", "text": "Cremation", "isCorrect": false },
        { "id": "b", "text": "Burial", "isCorrect": false },
        { "id": "c", "text": "Entombment", "isCorrect": false },
        { "id": "d", "text": "Examination", "isCorrect": true }
      ],
      "explanation": "Examination (autopsy) is a medical procedure, not a final disposal method like Burial or Cremation.",
      "hint": "Which one involves checking the body rather than final rest?"
    },
    {
      "id": "q33",
      "type": "multiple-choice",
      "question": "The line of command in the department of health records must be",
      "points": 1,
      "options": [
        { "id": "a", "text": "Effective", "isCorrect": false },
        { "id": "b", "text": "Accurate", "isCorrect": false },
        { "id": "c", "text": "Speed", "isCorrect": false },
        { "id": "d", "text": "Specified", "isCorrect": true }
      ],
      "explanation": "The chain of command must be clearly specified so everyone knows who they report to.",
      "hint": "It needs to be clearly defined."
    },
    {
      "id": "q34",
      "type": "multiple-choice",
      "question": "Ensure the gangway is at least _______ feet apart",
      "points": 1,
      "options": [
        { "id": "a", "text": "4", "isCorrect": false },
        { "id": "b", "text": "3", "isCorrect": true },
        { "id": "c", "text": "2", "isCorrect": false },
        { "id": "d", "text": "5", "isCorrect": false }
      ],
      "explanation": "The standard minimum width for a gangway (aisle) is 3 feet to allow safe passage.",
      "hint": "Standard aisle width."
    },
    {
      "id": "q35",
      "type": "multiple-choice",
      "question": "The section of the medical records department that arranges admission for emergency patients is called?",
      "points": 1,
      "options": [
        { "id": "a", "text": "Waiting list", "isCorrect": false },
        { "id": "b", "text": "Admission desk", "isCorrect": false },
        { "id": "c", "text": "Accident and Emergency wing", "isCorrect": false },
        { "id": "d", "text": "Bed bureau", "isCorrect": true }
      ],
      "explanation": "The Bed Bureau manages bed occupancy and arranges admissions.",
      "hint": "Which office manages the beds?"
    },
    {
      "id": "q36",
      "type": "multiple-choice",
      "question": "The following are sources of appointments except?",
      "points": 1,
      "options": [
        { "id": "a", "text": "Patients making calls", "isCorrect": false },
        { "id": "b", "text": "Health records officers making calls", "isCorrect": true },
        { "id": "c", "text": "Referrals", "isCorrect": false },
        { "id": "d", "text": "Physicians booking for their clients", "isCorrect": false }
      ],
      "explanation": "Appointments are initiated by patients or doctors. HRIOs process them but don't typically act as the 'source' of the clinical need for the appointment.",
      "hint": "Who usually asks for the appointment?"
    },
    {
      "id": "q37",
      "type": "multiple-choice",
      "question": "_____ is a document used for receiving goods from suppliers before storage",
      "points": 1,
      "options": [
        { "id": "a", "text": "S 11", "isCorrect": false },
        { "id": "b", "text": "S 3", "isCorrect": false },
        { "id": "c", "text": "S 13", "isCorrect": true },
        { "id": "d", "text": "S 10", "isCorrect": false }
      ],
      "explanation": "In Kenyan government procurement, S 13 is the Goods Received Note (Counter Receipt Voucher).",
      "hint": "S 11 is for issuing. Which one is for receiving?"
    },
    {
      "id": "q38",
      "type": "multiple-choice",
      "question": "The following are goals of designing Medical Records forms except?",
      "points": 1,
      "options": [
        { "id": "a", "text": "To provide guidance to form users", "isCorrect": false },
        { "id": "b", "text": "To improve the level of communication among health care providers", "isCorrect": false },
        { "id": "c", "text": "To reduce reproduction of many forms", "isCorrect": true },
        { "id": "d", "text": "To reduce duplication of information", "isCorrect": false }
      ],
      "explanation": "Reducing reproduction is a cost goal, not a primary design goal like usability, communication, or data efficiency.",
      "hint": "Which option is about printing costs rather than form function?"
    },
    {
      "id": "q39",
      "type": "multiple-choice",
      "question": "In strict alphabetical, surname, first name, Date of Birth (D.O.B) which of the following patients will be filed first in the master index?",
      "points": 1,
      "options": [
        { "id": "a", "text": "Odongo Maryann Atieno 16th January, 2014", "isCorrect": false },
        { "id": "b", "text": "Odongo Maryann Akoth 24th October, 1950", "isCorrect": false },
        { "id": "c", "text": "Odongo Maryann Adhiambo 13th February 1965", "isCorrect": true },
        { "id": "d", "text": "Odongo Maryann Ayoo 19th December, 2020", "isCorrect": false }
      ],
      "explanation": "Alphabetical order: Odongo (same) -> Maryann (same) -> Adhiambo (comes before Akoth, Atieno, Ayoo).",
      "hint": "Check the third name alphabetically."
    },
    {
      "id": "q40",
      "type": "multiple-choice",
      "question": "________ consent arises when records are disclosed to another medical agency for purpose of confirmed treatment",
      "points": 1,
      "options": [
        { "id": "a", "text": "Normal", "isCorrect": false },
        { "id": "b", "text": "Forced", "isCorrect": false },
        { "id": "c", "text": "Expressed", "isCorrect": false },
        { "id": "d", "text": "Implied", "isCorrect": true }
      ],
      "explanation": "Implied consent is assumed for continuity of care between providers.",
      "hint": "It is understood without being explicitly stated."
    },
    {
      "id": "q41",
      "type": "short-answer",
      "question": "Describe five ways of disposing patients attended to at the accident and emergency department",
      "points": 5,
      "acceptedAnswers": ["admission", "discharge", "referral", "transfer", "death", "mortuary", "home"],
      "explanation": "<div style='background:#f9f9f9; padding:15px; border-left:5px solid #2196F3;'><p><strong>Ways of Disposing Patients at A&E:</strong></p><ol><li><strong>Admission:</strong> Admitted to ward for care.</li><li><strong>Discharge Home:</strong> Treated and sent home.</li><li><strong>Referral to Clinic:</strong> Given appointment for follow-up.</li><li><strong>Transfer:</strong> Sent to another hospital.</li><li><strong>Brought in Dead (BID) / Death:</strong> Moved to mortuary.</li></ol></div>",
      "hint": "Think about where a patient can go after leaving the A&E room."
    },
    {
      "id": "q42",
      "type": "short-answer",
      "question": "Enumerate five Acts related to health records management",
      "points": 5,
      "acceptedAnswers": ["public health act", "mental health act", "medical practitioners", "data protection", "public archives", "evidence act", "cap 242"],
      "explanation": "<div style='background:#f9f9f9; padding:15px; border-left:5px solid #2196F3;'><p><strong>Key Acts:</strong></p><ul><li>Public Health Act (Cap 242)</li><li>Mental Health Act (Cap 248)</li><li>Medical Practitioners and Dentists Act (Cap 253)</li><li>Data Protection Act</li><li>Public Archives and Documentation Service Act</li><li>Evidence Act</li></ul></div>",
      "hint": "List 5 laws governing health info in Kenya."
    },
    {
      "id": "q43",
      "type": "short-answer",
      "question": "State five importance of quality assurance and quality improvement",
      "points": 5,
      "acceptedAnswers": ["safety", "efficiency", "standardization", "cost", "outcomes", "compliance"],
      "explanation": "<div style='background:#f9f9f9; padding:15px; border-left:5px solid #2196F3;'><p><strong>Importance of QA:</strong></p><ol><li>Improved Patient Safety</li><li>Enhanced Efficiency</li><li>Standardization of care</li><li>Cost Reduction</li><li>Better Clinical Outcomes</li><li>Compliance with standards</li></ol></div>",
      "hint": "Why do we check quality?"
    },
    {
      "id": "q44",
      "type": "short-answer",
      "question": "Identify five responsibilities of medical records committee",
      "points": 5,
      "acceptedAnswers": ["policy", "audit", "quality", "forms", "retention", "disposal"],
      "explanation": "<div style='background:#f9f9f9; padding:15px; border-left:5px solid #2196F3;'><p><strong>Responsibilities:</strong></p><ol><li>Policy Formulation</li><li>Quality Review/Audit</li><li>Form Design & Control</li><li>Retention & Disposal decisions</li><li>Standardization of coding</li></ol></div>",
      "hint": "What does the committee decide on?"
    },
    {
      "id": "q45",
      "type": "short-answer",
      "question": "Who are the members of the medical records committee?",
      "points": 5,
      "acceptedAnswers": ["superintendent", "hrio", "nurse", "clinician", "administrator"],
      "explanation": "<div style='background:#f9f9f9; padding:15px; border-left:5px solid #2196F3;'><p><strong>Members:</strong></p><ul><li>Medical Superintendent (Chair)</li><li>HRIO (Secretary)</li><li>Nursing Officer (Matron)</li><li>Clinicians/Consultants</li><li>Hospital Administrator</li></ul></div>",
      "hint": "List the job titles of the committee members."
    },
    {
      "id": "q46",
      "type": "short-answer",
      "question": "What are the benefits of electronic medical records?",
      "points": 5,
      "acceptedAnswers": ["accessibility", "storage", "retrieval", "legibility", "security", "backup"],
      "explanation": "<div style='background:#f9f9f9; padding:15px; border-left:5px solid #2196F3;'><p><strong>Benefits:</strong></p><ol><li>Accessibility (Multiple users)</li><li>Storage Efficiency (Less space)</li><li>Fast Retrieval</li><li>Legibility (No handwriting errors)</li><li>Clinical Decision Support</li><li>Data Backup & Security</li></ol></div>",
      "hint": "Why is a computer better than paper?"
    },
    {
      "id": "q47",
      "type": "short-answer",
      "question": "Enumerate five advantages of terminal digit filling",
      "points": 5,
      "acceptedAnswers": ["distribution", "even", "misfiling", "scalability", "security"],
      "explanation": "<div style='background:#f9f9f9; padding:15px; border-left:5px solid #2196F3;'><p><strong>Advantages:</strong></p><ol><li>Even distribution of files</li><li>Balanced workflow</li><li>Reduced misfiling</li><li>Scalability (Unlimited growth)</li><li>Security (Files scattered)</li></ol></div>",
      "hint": "Why use TDF over serial numbering?"
    },
    {
      "id": "q48",
      "type": "short-answer",
      "question": "Identify five causes of problems affecting quality in health care delivery",
      "points": 5,
      "acceptedAnswers": ["staffing", "resources", "communication", "training", "documentation", "leadership"],
      "explanation": "<div style='background:#f9f9f9; padding:15px; border-left:5px solid #2196F3;'><p><strong>Causes:</strong></p><ol><li>Inadequate Staffing</li><li>Lack of Resources/Equipment</li><li>Poor Communication</li><li>Inadequate Training</li><li>Poor Documentation</li><li>Lack of Leadership</li></ol></div>",
      "hint": "What makes hospital quality bad?"
    },
    {
      "id": "q49",
      "type": "short-answer",
      "question": "Explain the procedure of admitting a patient to the hospital (Long Answer)",
      "points": 20,
      "acceptedAnswers": ["authorization", "reception", "mpi", "registration", "file", "bed", "ward"],
      "explanation": "<div style='background:#f9f9f9; padding:15px; border-left:5px solid #2196F3;'><p><strong>Admission Procedure:</strong></p><ol><li><strong>Authorization:</strong> Doctor signs admission order.</li><li><strong>Reception:</strong> Check MPI for previous file.</li><li><strong>Data Collection:</strong> Register new/update old patient details.</li><li><strong>Documentation:</strong> Prepare file with forms.</li><li><strong>Financial:</strong> Clear insurance/payment.</li><li><strong>Bed Allocation:</strong> Bed Bureau assigns bed.</li><li><strong>Registers:</strong> Update Admission Register.</li><li><strong>Escort:</strong> Patient taken to ward.</li></ol></div>",
      "hint": "Walk through the steps from the doctor saying 'admit' to the patient arriving in the bed."
    }
  ]
}
