{
  "id": "bscn_paper_2_1768287363878_cda8f6c3-2c46-4039-a96f-892df54c04c1_004",
  "title": "Quiz 4: Roles & Functions of Community Health Nurse",
  "subjectId": "bscn_paper_2_1768287363878",
  "topicId": "cda8f6c3-2c46-4039-a96f-892df54c04c1",
  "topicName": "Unit 1: Introduction to Community Health",
  "description": "Test your ability to identify and describe the various roles and functions of a community health nurse.",
  "isPaid": true,
  "timeLimit": 20,
  "passingScore": 70,
  "version": 1,
  "order": 4,
  "questions": [
    {
      "id": "q1",
      "type": "matching",
      "question": "Match the nurse's role with the correct function:",
      "points": 20,
      "pairs": [
        { "id": "p1", "left": "Manager", "right": "Organizing and leading health care programs" },
        { "id": "p2", "left": "Advocator", "right": "Advising planners on community needs" },
        { "id": "p3", "left": "Health Educator", "right": "Teaching disease prevention" },
        { "id": "p4", "left": "Researcher", "right": "Carrying out surveys to identify problems" }
      ],
      "partialCredit": true,
      "explanation": "Manager=Leader; Advocator=Voice for community; Educator=Teacher; Researcher=Investigator.",
      "hint": "Link the job title to the action."
    },
    {
      "id": "q2",
      "type": "multiple-choice",
      "question": "Which role involves sharing technical health information with individual families and communities?",
      "points": 10,
      "options": [
        { "id": "a", "text": "Assessor", "isCorrect": false },
        { "id": "b", "text": "Evaluator", "isCorrect": false },
        { "id": "c", "text": "Advisor", "isCorrect": true },
        { "id": "d", "text": "Manager", "isCorrect": false }
      ],
      "explanation": "The Advisor role specifically involves sharing technical advice/information.",
      "hint": "Someone who gives counsel or advice."
    },
    {
      "id": "q3",
      "type": "fill-blank",
      "question": "As an ___BLANK___, the nurse identifies existing and potential health needs and resources in the community.",
      "points": 15,
      "blanks": [
        { "id": "blank1", "acceptedAnswers": ["Assessor", "assessor", "Identifier", "identifier"] }
      ],
      "caseSensitive": false,
      "explanation": "The Assessor/Identifier role involves evaluating the status and needs of the community.",
      "hint": "A role that involves checking or evaluating status."
    },
    {
      "id": "q4",
      "type": "multiple-select",
      "question": "Which functions fall under the 'Implementer' role? (Select all that apply)",
      "points": 15,
      "options": [
        { "id": "a", "text": "Creating community awareness", "isCorrect": true },
        { "id": "b", "text": "Executing health action/programs", "isCorrect": true },
        { "id": "c", "text": "Developing community ability to assess needs", "isCorrect": true },
        { "id": "d", "text": "Conducting scientific research studies", "isCorrect": false }
      ],
      "partialCredit": true,
      "explanation": "Research is a Researcher role. Implementer involves putting plans into action and building capacity.",
      "hint": "Actions that involve 'doing' or 'executing'."
    },
    {
      "id": "q5",
      "type": "true-false",
      "question": "The 'Evaluator' role is responsible for training other community health workers.",
      "points": 10,
      "correctAnswer": false,
      "explanation": "Training is the function of the **Trainer** role. The Evaluator assesses outcomes and performance.",
      "hint": "Evaluator measures success; Trainer teaches."
    },
    {
      "id": "q6",
      "type": "short-answer",
      "question": "What is the term for the broad areas of responsibility assumed by a nurse (e.g., the job they perform)?",
      "points": 10,
      "acceptedAnswers": ["function", "Function", "functions"],
      "caseSensitive": false,
      "explanation": "Function refers to the job or activities a nurse is expected to perform.",
      "hint": "It starts with 'F'."
    },
    {
      "id": "q7",
      "type": "multiple-choice",
      "question": "When a nurse plans for health action with other team members, they are acting in the role of:",
      "points": 10,
      "options": [
        { "id": "a", "text": "Evaluator", "isCorrect": false },
        { "id": "b", "text": "Planner", "isCorrect": true },
        { "id": "c", "text": "Trainer", "isCorrect": false },
        { "id": "d", "text": "Assessor", "isCorrect": false }
      ],
      "explanation": "The Planner role involves designing the course of action.",
      "hint": "The name of the role is in the question."
    },
    {
      "id": "q8",
      "type": "ordering",
      "question": "Arrange the logic flow of a nurse's intervention roles:",
      "points": 15,
      "items": [
        { "id": "i1", "text": "Assessor (Identifies problem)", "correctPosition": 1 },
        { "id": "i2", "text": "Planner (Designs solution)", "correctPosition": 2 },
        { "id": "i3", "text": "Implementer (Executes solution)", "correctPosition": 3 },
        { "id": "i4", "text": "Evaluator (Checks results)", "correctPosition": 4 }
      ],
      "partialCredit": true,
      "explanation": "The nursing process flow: Assess -> Plan -> Implement -> Evaluate.",
      "hint": "A-P-I-E."
    },
    {
      "id": "q9",
      "type": "true-false",
      "question": "The role of a community health nurse is strictly limited to hospital duties.",
      "points": 10,
      "correctAnswer": false,
      "explanation": "The role extends to the community to prevent illness and maximize health, not just hospital duties.",
      "hint": "Where does a 'community' health nurse work?"
    },
    {
      "id": "q10",
      "type": "multiple-choice",
      "question": "Who does the 'Trainer' role focus on teaching?",
      "points": 10,
      "options": [
        { "id": "a", "text": "Only patients", "isCorrect": false },
        { "id": "b", "text": "Only doctors", "isCorrect": false },
        { "id": "c", "text": "Other community health workers (designated & voluntary)", "isCorrect": true },
        { "id": "d", "text": "School children only", "isCorrect": false }
      ],
      "explanation": "The Trainer role specifically involves training other health workers and volunteers (CORPs).",
      "hint": "Think about capacity building."
    }
  ]
}