{
  "id": "nck_chn_b_new_research_proposal_report_1768763513728_ef9acbe5-5644-4106-a178-0850b3cf9026_003",
  "title": "Quiz 3: Lesson Planning & Teaching Skills",
  "subjectId": "nck_chn_b_new_research_proposal_report_1768763513728",
  "topicId": "ef9acbe5-5644-4106-a178-0850b3cf9026",
  "topicName": "Teaching Methodology in Nursing",
  "description": "Assess your ability to plan lessons effectively, write behavioral objectives, and apply micro-teaching skills.",
  "isPaid": true,
  "timeLimit": 20,
  "passingScore": 70,
  "version": 1,
  "order": 3,
  "questions": [
    {
      "id": "q3_1",
      "type": "multiple-select",
      "question": "Which of the following are essential components of a Lesson Plan?",
      "points": 15,
      "options": [
        { "id": "a", "text": "Specific Objectives", "isCorrect": true },
        { "id": "b", "text": "Teaching/Learning Activities", "isCorrect": true },
        { "id": "c", "text": "Evaluation Methods", "isCorrect": true },
        { "id": "d", "text": "Student Medical History", "isCorrect": false },
        { "id": "e", "text": "Time Allocation", "isCorrect": true }
      ],
      "partialCredit": true,
      "explanation": "A lesson plan includes objectives, content, methods, activities, resources, and evaluation. Medical history is irrelevant.",
      "hint": "Think about the structure of a class."
    },
    {
      "id": "q3_2",
      "type": "fill-blank",
      "question": "In the SMART acronym for objectives, 'M' stands for ___BLANK___ and 'T' stands for ___BLANK___.",
      "points": 10,
      "blanks": [
        { "id": "b1", "acceptedAnswers": ["measurable"] },
        { "id": "b2", "acceptedAnswers": ["time bound", "time-bound"] }
      ],
      "caseSensitive": false,
      "explanation": "SMART = Specific, Measurable, Achievable, Realistic, Time-bound.",
      "hint": "Can you count it? Is there a deadline?"
    },
    {
      "id": "q3_3",
      "type": "multiple-choice",
      "question": "Which part of a behavioral objective describes the minimum acceptable level of performance?",
      "points": 10,
      "options": [
        { "id": "a", "text": "Action Verb", "isCorrect": false },
        { "id": "b", "text": "Condition", "isCorrect": false },
        { "id": "c", "text": "Standard / Criteria", "isCorrect": true },
        { "id": "d", "text": "Introduction", "isCorrect": false }
      ],
      "explanation": "The Standard or Criteria defines how well the student must perform (e.g., 'with 90% accuracy').",
      "hint": "The yardstick for success."
    },
    {
      "id": "q3_4",
      "type": "matching",
      "question": "Match the Micro-Teaching skill to its definition:",
      "points": 20,
      "pairs": [
        { "id": "p1", "left": "Set Induction", "right": "Introducing the topic to capture attention" },
        { "id": "p2", "left": "Stimulus Variation", "right": "Changing voice, gestures, and movement" },
        { "id": "p3", "left": "Reinforcement", "right": "Rewarding students to promote good behavior" },
        { "id": "p4", "left": "Closure", "right": "Summarizing the main points at the end" }
      ],
      "partialCredit": true,
      "explanation": "Set Induction starts the lesson; Stimulus Variation keeps attention; Reinforcement encourages; Closure wraps up.",
      "hint": "Set = Start; Closure = End."
    },
    {
      "id": "q3_5",
      "type": "ordering",
      "question": "Order the steps in the Planning for Teaching process:",
      "points": 15,
      "items": [
        { "id": "i1", "text": "Determine objectives", "correctPosition": 1 },
        { "id": "i2", "text": "Select content", "correctPosition": 2 },
        { "id": "i3", "text": "Choose teaching methods", "correctPosition": 3 },
        { "id": "i4", "text": "Identify resources", "correctPosition": 4 },
        { "id": "i5", "text": "Plan evaluation", "correctPosition": 5 }
      ],
      "partialCredit": true,
      "explanation": "Objectives -> Content -> Methods -> Resources -> Evaluation.",
      "hint": "Start with the goal."
    },
    {
      "id": "q3_6",
      "type": "true-false",
      "question": "Verbs like 'know', 'understand', and 'appreciate' are suitable for behavioral objectives.",
      "points": 10,
      "correctAnswer": false,
      "explanation": "These verbs are vague and not directly observable. Behavioral objectives use action verbs like 'list', 'describe', 'demonstrate'.",
      "hint": "Can you see someone 'understanding'?"
    },
    {
      "id": "q3_7",
      "type": "short-answer",
      "question": "Name the characteristic of a good teacher that involves providing emotional support, praise, and encouragement.",
      "points": 10,
      "acceptedAnswers": ["warmth"],
      "caseSensitive": false,
      "partialMatch": false,
      "explanation": "Warmth refers to the teacher's friendly and supportive demeanor.",
      "hint": "Opposite of cold."
    },
    {
      "id": "q3_8",
      "type": "multiple-choice",
      "question": "What is the purpose of 'Questioning' during a lesson?",
      "points": 10,
      "options": [
        { "id": "a", "text": "To fill time", "isCorrect": false },
        { "id": "b", "text": "To intimidate students", "isCorrect": false },
        { "id": "c", "text": "To promote interaction and check understanding", "isCorrect": true },
        { "id": "d", "text": "To show the teacher's knowledge", "isCorrect": false }
      ],
      "explanation": "Questioning engages students, checks comprehension, and promotes active thinking.",
      "hint": "Interaction."
    },
    {
      "id": "q3_9",
      "type": "multiple-select",
      "question": "Which of the following are tasks of a teacher?",
      "points": 15,
      "options": [
        { "id": "a", "text": "Planning", "isCorrect": true },
        { "id": "b", "text": "Communication", "isCorrect": true },
        { "id": "c", "text": "Counselling", "isCorrect": true },
        { "id": "d", "text": "Providing Resources", "isCorrect": true },
        { "id": "e", "text": "Assessment", "isCorrect": true }
      ],
      "partialCredit": true,
      "explanation": "All listed options are core tasks of a teacher.",
      "hint": "All of them?"
    },
    {
      "id": "q3_10",
      "type": "fill-blank",
      "question": "___BLANK___ involves using varied teaching techniques to take into account the individual differences of learners.",
      "points": 10,
      "blanks": [
        { "id": "b1", "acceptedAnswers": ["individualizing", "individualize", "individualization"] }
      ],
      "caseSensitive": false,
      "explanation": "Individualizing instruction meets the diverse needs of students.",
      "hint": "Focus on the individual."
    }
  ]
}