{
  "id": "bscn_paper_i_1768130613347_9d4b07d4-6ec7-4f8c-924d-060837d3eaf6_002",
  "title": "Quiz 2: Adolescent Development & Life Skills",
  "subjectId": "bscn_paper_i_1768130613347",
  "topicId": "9d4b07d4-6ec7-4f8c-924d-060837d3eaf6",
  "topicName": "Unit One: Introduction to Reproductive Health",
  "description": "Evaluate your knowledge on adolescent biological changes, psychological needs, and essential life planning skills.",
  "isPaid": true,
  "timeLimit": 20,
  "passingScore": 70,
  "version": 1,
  "order": 2,
  "questions": [
    {
      "id": "q1",
      "type": "multiple-choice",
      "question": "What is the approximate age range for 'Adolescence' as generally shared by both sexes?",
      "points": 10,
      "options": [
        { "id": "a", "text": "9 - 14 years", "isCorrect": false },
        { "id": "b", "text": "13 - 18 years", "isCorrect": true },
        { "id": "c", "text": "18 - 24 years", "isCorrect": false },
        { "id": "d", "text": "15 - 21 years", "isCorrect": false }
      ],
      "explanation": "While onset varies, the two sexes share an approximate range marking adolescence from 13 - 18 years.",
      "hint": "It corresponds roughly to the teenage years."
    },
    {
      "id": "q2",
      "type": "matching",
      "question": "Match the hormone with its specific effect on secondary sexual characteristics:",
      "points": 20,
      "pairs": [
        { "id": "p1", "left": "Oestrogen", "right": "Breast development and hip broadening (Girls)" },
        { "id": "p2", "left": "Androgens", "right": "Voice deepening and muscular strength (Boys)" }
      ],
      "partialCredit": true,
      "explanation": "Oestrogen drives female secondary characteristics; Androgens drive male secondary characteristics.",
      "hint": "One is the primary female hormone, the other male."
    },
    {
      "id": "q3",
      "type": "multiple-select",
      "question": "Which of the following are psychological/emotional characteristics of adolescence? (Select all that apply)",
      "points": 15,
      "options": [
        { "id": "a", "text": "Pulling away from parents/seeking independence", "isCorrect": true },
        { "id": "b", "text": "Reduced influence of peers", "isCorrect": false },
        { "id": "c", "text": "Increased mood swings", "isCorrect": true },
        { "id": "d", "text": "Decreased interest in the opposite sex", "isCorrect": false }
      ],
      "partialCredit": true,
      "explanation": "Adolescents typically seek independence, value peer opinions highly, experience mood swings, and have increased interest in the opposite sex.",
      "hint": "Think about stereotypical teenage behavior."
    },
    {
      "id": "q4",
      "type": "fill-blank",
      "question": "The first ejaculation in boys is technically known as ___BLANK___.",
      "points": 15,
      "blanks": [
        { "id": "blank1", "acceptedAnswers": ["spermache", "Spermache"] }
      ],
      "caseSensitive": false,
      "explanation": "Spermache refers to the first ejaculation, often occurring as nocturnal emissions (wet dreams).",
      "hint": "It sounds similar to 'menarche' but for sperm."
    },
    {
      "id": "q5",
      "type": "multiple-choice",
      "question": "Based on the text provided, what is the prevalence of HIV among female adolescents aged 15-19 in Kenya?",
      "richContent": {
        "type": "html",
        "content": "<div style='background:#f9f9f9; padding:15px; border:1px solid #ccc;'><strong>Statistics:</strong><br><ul><li>20% of adolescents sexually active by 14</li><li>HIV prevalence (Females 15-19): <strong>22.3%</strong></li><li>HIV prevalence (Males 15-19): <strong>4.2%</strong></li></ul></div>"
      },
      "points": 15,
      "options": [
        { "id": "a", "text": "4.2%", "isCorrect": false },
        { "id": "b", "text": "10%", "isCorrect": false },
        { "id": "c", "text": "22.3%", "isCorrect": true },
        { "id": "d", "text": "45%", "isCorrect": false }
      ],
      "explanation": "HIV prevalence among female adolescents (15-19) stands at 22.3%, significantly higher than males (4.2%).",
      "hint": "Look closely at the data in the box."
    },
    {
      "id": "q6",
      "type": "short-answer",
      "question": "Which life skill is defined as 'being confident and able to make a stand on one's words, actions or beliefs', such as saying NO to drugs?",
      "points": 15,
      "acceptedAnswers": ["Assertiveness", "assertiveness"],
      "caseSensitive": false,
      "explanation": "Assertiveness includes the ability to say NO to drugs or sexual advances based on one's beliefs without being aggressive.",
      "hint": "It starts with 'A'."
    },
    {
      "id": "q7",
      "type": "true-false",
      "question": "Research confirms that providing sex education to young people leads to earlier and increased sexual activity.",
      "points": 10,
      "correctAnswer": false,
      "explanation": "Studies have shown that sex education leads to safer behavior and does NOT encourage earlier or increased sexual activity.",
      "hint": "Does knowledge generally lead to recklessness or responsibility?"
    },
    {
      "id": "q8",
      "type": "multiple-select",
      "question": "Which of the following principles should be applied when working with young people? (Select all that apply)",
      "points": 15,
      "options": [
        { "id": "a", "text": "Identify and encourage peer leadership", "isCorrect": true },
        { "id": "b", "text": "Ensure privacy and confidentiality", "isCorrect": true },
        { "id": "c", "text": "Refer to providers of the same sex where possible", "isCorrect": true },
        { "id": "d", "text": "Treat them exactly like adults", "isCorrect": false }
      ],
      "partialCredit": true,
      "explanation": "Young people have specific needs: they require privacy, confidentiality, and often respond better to peers or same-sex providers.",
      "hint": "Consider what makes a teenager comfortable seeking help."
    },
    {
      "id": "q9",
      "type": "ordering",
      "question": "Order the following steps in a logical decision-making process for an adolescent facing a dilemma:",
      "points": 20,
      "items": [
        { "id": "item1", "text": "Identify the problem", "correctPosition": 1 },
        { "id": "item2", "text": "Gather accurate information/facts", "correctPosition": 2 },
        { "id": "item3", "text": "Weigh consequences of available choices", "correctPosition": 3 },
        { "id": "item4", "text": "Make the decision and take responsibility", "correctPosition": 4 }
      ],
      "partialCredit": true,
      "explanation": "Problem ID -> Info gathering -> Weighing options -> Action/Responsibility.",
      "hint": "You can't weigh choices before knowing the facts."
    },
    {
      "id": "q10",
      "type": "multiple-choice",
      "question": "Which of the following is NOT a right of assertiveness?",
      "points": 10,
      "options": [
        { "id": "a", "text": "Right to expression", "isCorrect": false },
        { "id": "b", "text": "Right to set priorities", "isCorrect": false },
        { "id": "c", "text": "Right to intimidate others", "isCorrect": true },
        { "id": "d", "text": "Right to refuse requests without guilt", "isCorrect": false }
      ],
      "explanation": "Assertiveness involves standing up for oneself WITHOUT violating the rights of others or intimidating them.",
      "hint": "Assertiveness is positive; aggression is negative."
    }
  ]
}